pyharry100/__init__.py
pyharry100/main.py
pyharry100-0.1.1.dist-info/METADATA
pyharry100-0.1.1.dist-info/WHEEL
pyharry100-0.1.1.dist-info/entry_points.txt
pyharry100-0.1.1.dist-info/top_level.txt
pyharry100-0.1.1.dist-info/RECORD
