Metadata-Version: 2.2
Name: pyharry100
Version: 0.1.1
Summary: A CLI tool designed to help beginners efficiently learn Python through the 100 Days of Code challenge by CodeWithHarry. It provides structured learning with notes, extra in-depth notes, tasks, and additional challenges. Users can also explore recommended content for deeper knowledge after each day's video.
Home-page: https://github.com/Zain-Zameer/pyharry100
Author: Muhammad Zain Zameer
Author-email: officialmuhammadzain45@gmail.com
Classifier: Programming Language :: Python :: 3
Classifier: License :: OSI Approved :: MIT License
Classifier: Operating System :: OS Independent
Requires-Python: >=3.6
Requires-Dist: requests
Dynamic: author
Dynamic: author-email
Dynamic: classifier
Dynamic: description
Dynamic: description-content-type
Dynamic: home-page
Dynamic: requires-dist
Dynamic: requires-python
Dynamic: summary
